g2pL/__init__.py
g2pL/class2idx.pkl
g2pL/g2pL.py
g2pL/matched_word.txt
g2pL/model.py
g2pL/pinyin_dic.json
g2pL/polyphone_dic.json
g2pL/tone2totone1.json
g2pL/utils.py
g2pL/vocab.py
g2pL/bert_config/README.md
g2pL/bert_config/config_g2pL.json
g2pL/bert_config/tokenizer.json
g2pL/bert_config/tokenizer_config.json
g2pL/bert_config/vocab.txt
g2pL-0.0.19.dist-info/LICENSE
g2pL-0.0.19.dist-info/METADATA
g2pL-0.0.19.dist-info/WHEEL
g2pL-0.0.19.dist-info/top_level.txt
g2pL-0.0.19.dist-info/RECORD
