Metadata-Version: 2.1
Name: g2pL
Version: 0.0.19
Summary: Polyphone disambiguation for g2p
Home-page: https://github.com/whzikaros/g2pL
Author: HongZhi Wan
Author-email: whzikaros@gmail.com
License: Apache License 2.0
Platform: UNKNOWN
Classifier: Development Status :: 5 - Production/Stable
Classifier: Intended Audience :: Developers
Classifier: Intended Audience :: Science/Research
Classifier: License :: OSI Approved :: Apache Software License
Classifier: Operating System :: OS Independent
Classifier: Programming Language :: Python :: 3
Requires-Python: >=3.6
License-File: LICENSE
Requires-Dist: transformers (==3.4.0)
Requires-Dist: opencc (==1.1.3)
Requires-Dist: requests (==2.28.1)
